LICENSE.txt
MANIFEST.in
README.rst
setup.py
color_me/__init__.py
color_me.egg-info/PKG-INFO
color_me.egg-info/SOURCES.txt
color_me.egg-info/dependency_links.txt
color_me.egg-info/not-zip-safe
color_me.egg-info/top_level.txt
docs/Makefile
docs/conf.py
docs/index.rst
tests/.coveragerc
tests/pytest.ini